{
  "version": 2,
  "location": "dj2:alloy_kiln_helper",
  "traits": {},
  "properties": {
    "rotationState": "ALL",
    "showInJei": true,
    "isOpaque": true,
    "hasCollision": true,
    "destroyTime": 1.5,
    "explosionResistance": 10.0,
    "harvestLevel": 1,
    "stackSize": 64,
    "tabGroup": "multiblocked"
  },
  "status": {
    "unformed": {
      "renderer": {
        "state": {
          "id": "immersiveengineering:stone_decoration",
          "meta": 10
        },
        "type": "blockstate"
      }
    },
    "idle": {
      "parent": "unformed"
    },
    "working": {
      "parent": "idle"
    },
    "suspend": {
      "parent": "working"
    }
  },
  "recipeMap": "empty",
  "basePattern": {
    "structureDir": [
      "LEFT",
      "UP",
      "BACK"
    ],
    "pattern": [
      [
        "@A",
        "AA"
      ],
      [
        "AA",
        "AA"
      ]
    ],
    "aisleRepetitions": [
      [
        1,
        1
      ],
      [
        1,
        1
      ]
    ],
    "predicates": {
      "A": {
        "states": [
          {
            "id": "immersiveengineering:stone_decoration",
            "meta": 10
          }
        ],
        "type": "states"
      },
      "controller": {
        "location": "dj2:alloy_kiln_helper",
        "type": "component"
      },
      "air": {
        "type": "air"
      },
      "any": {
        "type": "any"
      }
    },
    "symbolMap": {
      "@": [
        "controller"
      ],
      " ": [
        "any"
      ],
      "A": [
        "A"
      ],
      "-": [
        "air"
      ]
    }
  }
}
